simglucose/__init__.py
simglucose/utils.py
simglucose/actuator/__init__.py
simglucose/actuator/pump.py
simglucose/analysis/__init__.py
simglucose/analysis/report.py
simglucose/analysis/risk.py
simglucose/controller/__init__.py
simglucose/controller/basal_bolus_ctrller.py
simglucose/controller/base.py
simglucose/controller/pid_ctrller.py
simglucose/envs/__init__.py
simglucose/envs/simglucose_gym_env.py
simglucose/params/Quest.csv
simglucose/params/pump_params.csv
simglucose/params/sensor_params.csv
simglucose/params/vpatient_params.csv
simglucose/patient/__init__.py
simglucose/patient/base.py
simglucose/patient/t1dpatient.py
simglucose/sensor/__init__.py
simglucose/sensor/cgm.py
simglucose/sensor/noise_gen.py
simglucose/simulation/__init__.py
simglucose/simulation/env.py
simglucose/simulation/rendering.py
simglucose/simulation/scenario.py
simglucose/simulation/scenario_gen.py
simglucose/simulation/sim_engine.py
simglucose/simulation/user_interface.py
simglucose-0.2.11.dist-info/LICENSE
simglucose-0.2.11.dist-info/METADATA
simglucose-0.2.11.dist-info/WHEEL
simglucose-0.2.11.dist-info/top_level.txt
simglucose-0.2.11.dist-info/RECORD
