Metadata-Version: 2.1
Name: simglucose
Version: 0.2.11
Summary: A Type-1 Diabetes Simulator as a Reinforcement Learning Environment in OpenAI gym or rllab (python implementation of UVa/Padova Simulator)
Home-page: https://github.com/jxx123/simglucose
Author: Jinyu Xie
Author-email: xjygr08@gmail.com
License: MIT
Platform: UNKNOWN
Requires-Dist: gym (==0.9.4)
Requires-Dist: gymnasium (~=0.29.1)
Requires-Dist: pathos (>=0.3.1)
Requires-Dist: scipy (>=1.11.0)
Requires-Dist: matplotlib (>=3.7.2)
Requires-Dist: numpy (>=1.25.0)
Requires-Dist: pandas (>=2.0.3)
